{
  "id": "share-copy-fail",
  "name": "share-copy-fail",
  "title": "分享按钮复制失败修复",
  "description": "",
  "status": "completed",
  "dev_type": null,
  "scope": null,
  "package": null,
  "priority": "P2",
  "creator": "nico",
  "assignee": "nico",
  "createdAt": "2026-06-26",
  "completedAt": "2026-06-26",
  "branch": "trellisx-06-26-share-copy-fail",
  "base_branch": "master",
  "worktree_path": ".worktrees/06-26-share-copy-fail",
  "commit": null,
  "pr_url": null,
  "subtasks": [],
  "children": [],
  "parent": null,
  "relatedFiles": [],
  "notes": "",
  "meta": {}
}